tomtom_api/__init__.py
tomtom_api/__main__.py
tomtom_api/cli.py
tomtom_api/client.py
tomtom_api/priority_queue/__init__.py
tomtom_api/priority_queue/cli.py
tomtom_api/priority_queue/lib.py
tomtom_api/priority_queue/models/__init__.py
tomtom_api/priority_queue/models/daemon.py
tomtom_api/priority_queue/models/database.py
tomtom_api/priority_queue/models/queue.py
tomtom_api/priority_queue/models/status.py
tomtom_api/traffic_stats/__init__.py
tomtom_api/traffic_stats/models/__init__.py
tomtom_api/traffic_stats/models/geospatial.py
tomtom_api/traffic_stats/models/responses.py
tomtom_api/traffic_stats/models/status.py
tomtom_api/traffic_stats/models/time.py
tomtom_api/traffic_stats/models/jobs/__init__.py
tomtom_api/traffic_stats/models/jobs/area.py
tomtom_api/traffic_stats/models/jobs/base.py
tomtom_api/traffic_stats/models/jobs/route.py
tomtom_api/traffic_stats/models/jobs/traffic_density.py
tomtom_api/utils/__init__.py
tomtom_api/utils/daemon.py
tomtom_api/utils/exceptions.py
tomtom_api/utils/geospatial.py
tomtom_api/utils/internal.py
tomtom_api/utils/singleton.py
tomtom_api/utils/time.py
tomtom_api-2024.12.5.dist-info/entry_points.txt
tomtom_api-2024.12.5.dist-info/WHEEL
tomtom_api-2024.12.5.dist-info/METADATA
tomtom_api-2024.12.5.dist-info/RECORD
