Metadata-Version: 2.3
Name: tomtom_api
Version: 2024.12.5
Summary: API client allowing to interact with the tomtom REST services.
Author-email: Guillaume Latour <guillaume.latour@macq.eu>
Maintainer-email: Guillaume Latour <guillaume.latour@macq.eu>
Requires-Python: >=3.8
Requires-Dist: click
Requires-Dist: pytz
Requires-Dist: requests
Requires-Dist: shapely
Requires-Dist: dataclass-wizard
Requires-Dist: pandas
Requires-Dist: pyarrow
Requires-Dist: tabulate
Requires-Dist: geojson
Requires-Dist: ruff ; extra == "dev"
Requires-Dist: pytest ; extra == "dev"
Requires-Dist: pyproj ; extra == "pyproj"
Project-URL: repository, https://stash.macq.eu/projects/RDDS/repos/tomtom-api
Provides-Extra: dev
Provides-Extra: pyproj
